dev/__init__.py
graph4nlp/__init__.py
graph4nlp/pytorch/__init__.py
graph4nlp/pytorch/data/__init__.py
graph4nlp/pytorch/data/data.py
graph4nlp/pytorch/data/dataset.py
graph4nlp/pytorch/data/profiling.py
graph4nlp/pytorch/data/utils.py
graph4nlp/pytorch/data/views.py
graph4nlp/pytorch/datasets/__init__.py
graph4nlp/pytorch/datasets/cnn.py
graph4nlp/pytorch/datasets/geo.py
graph4nlp/pytorch/datasets/jobs.py
graph4nlp/pytorch/datasets/kinship.py
graph4nlp/pytorch/datasets/mathqa.py
graph4nlp/pytorch/datasets/mawps.py
graph4nlp/pytorch/datasets/squad.py
graph4nlp/pytorch/datasets/trec.py
graph4nlp/pytorch/inference_wrapper/__init__.py
graph4nlp/pytorch/inference_wrapper/base.py
graph4nlp/pytorch/inference_wrapper/classifier_inference_wrapper.py
graph4nlp/pytorch/inference_wrapper/generator_inference_wrapper.py
graph4nlp/pytorch/inference_wrapper/generator_inference_wrapper_for_tree.py
graph4nlp/pytorch/models/__init__.py
graph4nlp/pytorch/models/base.py
graph4nlp/pytorch/models/graph2seq.py
graph4nlp/pytorch/models/graph2seq_loss.py
graph4nlp/pytorch/models/graph2tree.py
graph4nlp/pytorch/modules/__init__.py
graph4nlp/pytorch/modules/config/__init__.py
graph4nlp/pytorch/modules/config/graph_construction/__init__.py
graph4nlp/pytorch/modules/config/graph_construction/constituency.yaml
graph4nlp/pytorch/modules/config/graph_construction/dependency.yaml
graph4nlp/pytorch/modules/config/graph_construction/ie_graph_construction.yaml
graph4nlp/pytorch/modules/config/graph_construction/node_emb.yaml
graph4nlp/pytorch/modules/config/graph_construction/node_emb_refine.yaml
graph4nlp/pytorch/modules/config/graph_embedding/__init__.py
graph4nlp/pytorch/modules/config/graph_embedding/gat.yaml
graph4nlp/pytorch/modules/config/graph_embedding/gcn.yaml
graph4nlp/pytorch/modules/config/graph_embedding/ggnn.yaml
graph4nlp/pytorch/modules/config/graph_embedding/graphsage.yaml
graph4nlp/pytorch/modules/config/graph_initialization/__init__.py
graph4nlp_cu110-0.5.5.dist-info/LICENSE
graph4nlp_cu110-0.5.5.dist-info/METADATA
graph4nlp_cu110-0.5.5.dist-info/WHEEL
graph4nlp_cu110-0.5.5.dist-info/top_level.txt
graph4nlp_cu110-0.5.5.dist-info/RECORD
